rectools/__init__.py
rectools/columns.py
rectools/compat.py
rectools/dataset/__init__.py
rectools/dataset/context.py
rectools/dataset/dataset.py
rectools/dataset/features.py
rectools/dataset/identifiers.py
rectools/dataset/interactions.py
rectools/dataset/torch_datasets.py
rectools/exceptions.py
rectools/metrics/__init__.py
rectools/metrics/auc.py
rectools/metrics/base.py
rectools/metrics/catalog.py
rectools/metrics/classification.py
rectools/metrics/debias.py
rectools/metrics/distances.py
rectools/metrics/diversity.py
rectools/metrics/dq.py
rectools/metrics/intersection.py
rectools/metrics/novelty.py
rectools/metrics/popularity.py
rectools/metrics/ranking.py
rectools/metrics/scoring.py
rectools/metrics/serendipity.py
rectools/model_selection/__init__.py
rectools/model_selection/cross_validate.py
rectools/model_selection/last_n_split.py
rectools/model_selection/random_split.py
rectools/model_selection/splitter.py
rectools/model_selection/time_split.py
rectools/model_selection/utils.py
rectools/models/__init__.py
rectools/models/base.py
rectools/models/ease.py
rectools/models/implicit_als.py
rectools/models/implicit_bpr.py
rectools/models/implicit_knn.py
rectools/models/lightfm.py
rectools/models/nn/__init__.py
rectools/models/nn/dssm.py
rectools/models/nn/item_net.py
rectools/models/nn/transformers/__init__.py
rectools/models/nn/transformers/base.py
rectools/models/nn/transformers/bert4rec.py
rectools/models/nn/transformers/constants.py
rectools/models/nn/transformers/data_preparator.py
rectools/models/nn/transformers/hstu.py
rectools/models/nn/transformers/lightning.py
rectools/models/nn/transformers/ligr.py
rectools/models/nn/transformers/negative_sampler.py
rectools/models/nn/transformers/net_blocks.py
rectools/models/nn/transformers/sasrec.py
rectools/models/nn/transformers/similarity.py
rectools/models/nn/transformers/torch_backbone.py
rectools/models/nn/transformers/utils.py
rectools/models/popular.py
rectools/models/popular_in_category.py
rectools-0.17.0.dist-info/LICENSE
rectools-0.17.0.dist-info/METADATA
rectools-0.17.0.dist-info/WHEEL
rectools-0.17.0.dist-info/RECORD
