Metadata-Version: 2.1
Name: RecTools
Version: 0.17.0
Summary: An easy-to-use Python library for building recommendation systems
Home-page: https://github.com/MobileTeleSystems/RecTools
License: Apache-2.0
Keywords: recsys,recommendation systems,machine learning,AI,personalization
Author: Emiliy Feldman
Author-email: feldlime@yandex.ru
Maintainer: Emiliy Feldman
Maintainer-email: feldlime@yandex.ru
Requires-Python: >=3.9,<3.14
Classifier: Development Status :: 3 - Alpha
Classifier: Intended Audience :: Education
Classifier: Intended Audience :: Science/Research
Classifier: License :: OSI Approved :: Apache Software License
Classifier: Operating System :: MacOS
Classifier: Operating System :: Microsoft :: Windows
Classifier: Operating System :: Unix
Classifier: Programming Language :: Python :: 3
Classifier: Programming Language :: Python :: 3.9
Classifier: Programming Language :: Python :: 3.10
Classifier: Programming Language :: Python :: 3.11
Classifier: Programming Language :: Python :: 3.12
Classifier: Programming Language :: Python :: 3.13
Classifier: Topic :: Scientific/Engineering :: Artificial Intelligence
Classifier: Topic :: Software Development :: Libraries :: Python Modules
Provides-Extra: all
Provides-Extra: cupy
Provides-Extra: lightfm
Provides-Extra: nmslib
Provides-Extra: torch
Provides-Extra: visuals
Requires-Dist: attrs (>=19.1.0,<24.0.0)
Requires-Dist: cupy-cuda12x (>=13.3.0,<14.0.0) ; (sys_platform != "darwin" and python_version < "3.13") and (extra == "cupy" or extra == "all")
Requires-Dist: cupy-cuda12x (>=13.4.0,<14.0.0) ; (sys_platform != "darwin" and python_version >= "3.13") and (extra == "cupy" or extra == "all")
Requires-Dist: fastrlock (>=0.8.3,<0.9.0) ; sys_platform != "darwin"
Requires-Dist: implicit (>=0.7.1,<0.8.0)
Requires-Dist: ipywidgets (>=7.7,<8.2) ; extra == "visuals" or extra == "all"
Requires-Dist: nbformat (>=4.2.0) ; extra == "visuals" or extra == "all"
Requires-Dist: nmslib (>=2.0.4,<3.0.0) ; (python_version < "3.11") and (extra == "nmslib" or extra == "all")
Requires-Dist: nmslib-metabrainz (>=2.1.3,<3.0.0) ; (python_version >= "3.11" and python_version < "3.13") and (extra == "nmslib" or extra == "all")
Requires-Dist: numpy (>=1.22,<2.0.0) ; python_version < "3.12"
Requires-Dist: numpy (>=1.26,<2.0.0) ; python_version == "3.12"
Requires-Dist: numpy (>=2.1.0,<3.0.0) ; python_version >= "3.13"
Requires-Dist: pandas (>=1.5.0,<3.0.0) ; python_version < "3.13"
Requires-Dist: pandas (>=2.2.3,<3.0.0) ; python_version >= "3.13"
Requires-Dist: plotly (>=5.22.0,<6.0.0) ; extra == "visuals" or extra == "all"
Requires-Dist: pydantic (>=2.8.2,<3.0.0)
Requires-Dist: pydantic-core (>=2.20.1,<3.0.0)
Requires-Dist: pytorch-lightning (>=1.6.0,<3.0.0) ; (python_version < "3.13") and (extra == "torch" or extra == "all")
Requires-Dist: pytorch-lightning (>=2.5.1,<3.0.0) ; (python_version >= "3.13") and (extra == "torch" or extra == "all")
Requires-Dist: rectools-lightfm (>=1.17.3,<2.0.0) ; extra == "lightfm" or extra == "all"
Requires-Dist: scipy (>=1.10.1,<1.13) ; python_version < "3.10"
Requires-Dist: scipy (>=1.14.1,<2.0.0) ; python_version >= "3.10"
Requires-Dist: torch (>=1.6.0,<2.3.0) ; (sys_platform == "darwin" and platform_machine == "x86_64" and python_version < "3.13") and (extra == "torch" or extra == "all")
Requires-Dist: torch (>=1.6.0,<3.0.0) ; (python_version < "3.13") and (extra == "torch" or extra == "all")
Requires-Dist: torch (>=2.6.0,<3.0.0) ; (python_version >= "3.13") and (extra == "torch" or extra == "all")
Requires-Dist: tqdm (>=4.27.0,<5.0.0)
Requires-Dist: typeguard (>=4.1.0,<5.0.0)
Requires-Dist: typing-extensions (>=4.12.2,<5.0.0)
Project-URL: Documentation, https://rectools.readthedocs.io
Project-URL: Repository, https://github.com/MobileTeleSystems/RecTools
